{
  "0xd9": "IJyKb",
  "0xda": "user",
  "0xdb": "...",
  "0xdc": "\n                        <img src=\"",
  "0xdd": "b8b07b9f4b4ea48a8dfdbf2ff2344bca5721b369",
  "0xde": "IEVpo",
  "0xdf": "location",
  "0xe0": "ewybf",
  "0xe1": "indexOf",
  "0xe2": "\n                    <div style=\"flex: 1; overflow: hidden;\">\n                        <div class=\"title\">",
  "0xe3": "UQcSc",
  "0xe4": ".message",
  "0xe5": "YUyvx",
  "0xe6": "YLlTh",
  "0xe7": "history-modal",
  "0xe8": "mhDuE",
  "0xe9": "You are an expert Prompt Engineer. Your task is to rewrite the user's prompt to be more detailed, structured, and clear. \n\nGuidelines:\n1. **Improve Quality**: Fix grammar, clarify ambiguity, and expand on the user's core idea.\n2. **Respect Intent**: Do NOT add specific frameworks (like React, Tailwind, Python) unless the user explicitly mentioned them.\n3. **Structure**: Use bullet points or sections if it helps clarity.\n4. **Output**: Return ONLY the improved prompt text. Do not add conversational filler.",
  "0xea": "xGhFg",
  "0xeb": "file-preview-container",
  "0xec": "error",
  "0xed": "ZpYgf",
  "0xee": "none",
  "0xef": "gufEr",
  "0xf0": "jADHq",
  "0xf1": "stringify",
  "0xf2": "input",
  "0xf3": "kBCjk",
  "0xf4": "iJhRc",
  "0xf5": "query",
  "0xf6": "data",
  "0xf7": "scrollTop",
  "0xf8": "neNFa",
  "0xf9": "</div>\n                        <span class=\"file-name\" title=\"",
  "0xfa": "mVlII",
  "0xfb": "pfNJN",
  "0xfc": "image-modal",
  "0xfd": ".credits-value",
  "0xfe": "filter",
  "0xff": "aAGIP",
  "0x100": "Tem certeza que deseja apagar este chat?",
  "0x101": "BYgjy",
  "0x102": "newValue",
  "0x103": ".status-indicator",
  "0x104": "AbqAR",
  "0x105": "BWKoN",
  "0x106": "zcGBx",
  "0x107": "JBVlG",
  "0x108": "tpSfJ",
  "0x109": "bKJNz",
  "0x10a": "zHQZU",
  "0x10b": "DddPl",
  "0x10c": "dqYgv",
  "0x10d": "getElementById",
  "0x10e": "mediaDevices",
  "0x10f": "BBhOt",
  "0x110": "isArray",
  "0x111": "SwpJC",
  "0x112": ".status-dot",
  "0x113": "preventDefault",
  "0x114": "LYExp",
  "0x115": "keydown",
  "0x116": "getUserMedia",
  "0x117": "tsvnY",
  "0x118": "Digite algo primeiro...",
  "0x119": "XxyiH",
  "0x11a": "reply",
  "0x11b": "gRGwT",
  "0x11c": "Erro: ",
  "0x11d": "system",
  "0x11e": "results",
  "0x11f": "Error reading files",
  "0x120": "5|0|2|1|3|4",
  "0x121": "index",
  "0x122": "doHpX",
  "0x123": "vlDqi",
  "0x124": "StIwQ",
  "0x125": "aXuQX",
  "0x126": "img",
  "0x127": "ClkhL",
  "0x128": "lbYjq",
  "0x129": "UdgGL",
  "0x12a": "text",
  "0x12b": "Imagem colada com sucesso!",
  "0x12c": "661436IVYvho",
  "0x12d": "#ef4444",
  "0x12e": "iINue",
  "0x12f": "YgXwO",
  "0x130": "XzwPQ",
  "0x131": "href",
  "0x132": "success",
  "0x133": "start",
  "0x134": "auth.html",
  "0x135": "YqGqZ",
  "0x136": "BtpmB",
  "0x137": "pjIIW",
  "0x138": "MANAI",
  "0x139": "fYana",
  "0x13a": "GVxbu",
  "0x13b": "DOMContentLoaded",
  "0x13c": "KOVss",
  "0x13d": "borderColor",
  "0x13e": "toLocaleDateString",
  "0x13f": "items",
  "0x140": "Erro no envio",
  "0x141": "sAEzM",
  "0x142": "message system",
  "0x143": "innerText",
  "0x144": "assistant",
  "0x145": "MUoIt",
  "0x146": "getCredits",
  "0x147": "authTimestamp",
  "0x148": "rgba(239, 68, 68, 0.1)",
  "0x149": "DqIdC",
  "0x14a": "suNhw",
  "0x14b": "userData",
  "0x14c": "lastError",
  "0x14d": "attachment-item",
  "0x14e": "aVXEi",
  "0x14f": "length",
  "0x150": "UVNNv",
  "0x151": "ezEFD",
  "0x152": "rTnDa",
  "0x153": "map",
  "0x154": "Uymsk",
  "0x155": "GCUhs",
  "0x156": "HGsVZ",
  "0x157": "MRXFl",
  "0x158": "lrRhS",
  "0x159": "xDAFG",
  "0x15a": "files",
  "0x15b": "projectId",
  "0x15c": "lYqnr",
  "0x15d": "SsdCZ",
  "0x15e": "DiLvE",
  "0x15f": "height",
  "0x160": "Deseja realmente desconectar da sua licença?",
  "0x161": "Erro na revalidação:",
  "0x162": "proxy_webhook",
  "0x163": "message-content",
  "0x164": "SbJQN",
  "0x165": "dAoRx",
  "0x166": "55WJSpGr",
  "0x167": "\" title=\"Remover\">\n                            <svg xmlns=\"http://www.w3.org/2000/svg\" width=\"14\" height=\"14\" viewBox=\"0 0 24 24\" fill=\"none\" stroke=\"currentColor\" stroke-width=\"2\" stroke-linecap=\"round\" stroke-linejoin=\"round\"><line x1=\"18\" y1=\"6\" x2=\"6\" y2=\"18\"></line><line x1=\"6\" y1=\"6\" x2=\"18\" y2=\"18\"></line></svg>\n                        </button>\n                    ",
  "0x168": "mic-btn",
  "0x169": "tGAcj",
  "0x16a": "6138714OIUHSW",
  "0x16b": "logout-btn",
  "0x16c": "novqE",
  "0x16d": "yNLVv",
  "0x16e": "Delkj",
  "0x16f": "mistral-small",
  "0x170": "3669219xZqXta",
  "0x171": "startsWith",
  "0x172": "message-attachments",
  "0x173": "rAlDW",
  "0x174": "TfAJv",
  "0x175": "sessionToken",
  "0x176": "PdoWb",
  "0x177": "find",
  "0x178": ".message-content",
  "0x179": "innerHTML",
  "0x17a": "hoopS",
  "0x17b": "Projeto Publicado com Sucesso! 🚀",
  "0x17c": "ylFwb",
  "0x17d": "DYtze",
  "0x17e": "hKbEj",
  "0x17f": "permissionGranted",
  "0x180": "message ",
  "0x181": "transcript",
  "0x182": "iKOuw",
  "0x183": "key",
  "0x184": "4FBZpgW",
  "0x185": "RVnLh",
  "0x186": "ZfBOW",
  "0x187": "remove",
  "0x188": "⚠️ Arquivos maiores que 5MB foram ignorados.",
  "0x189": "jbPho",
  "0x18a": "retry-btn",
  "0x18b": "nutJz",
  "0x18c": "choices",
  "0x18d": "YDlEw",
  "0x18e": "messages",
  "0x18f": "cmIPL",
  "0x190": "name",
  "0x191": "continuous",
  "0x192": "charAt",
  "0x193": "TloZE",
  "0x194": "lgaQO",
  "0x195": "unshift",
  "0x196": "NRsiw",
  "0x197": "ZNHbo",
  "0x198": "classList",
  "0x199": "token",
  "0x19a": "Iniciando backup do projeto... 📦",
  "0x19b": "657699sPWhVp",
  "0x19c": "ATIVO",
  "0x19d": "lLKNO",
  "0x19e": "target",
  "0x19f": "title",
  "0x1a0": "BWIHz",
  "0x1a1": "disabled",
  "0x1a2": "onMessage",
  "0x1a3": "qFuPm",
  "0x1a4": "onresult",
  "0x1a5": "div",
  "0x1a6": "iYIOU",
  "0x1a7": "GLzWr",
  "0x1a8": "createElement",
  "0x1a9": "forEach",
  "0x1aa": "sisMC",
  "0x1ab": "NPPbA",
  "0x1ac": "onerror",
  "0x1ad": "createObjectURL",
  "0x1ae": "windows",
  "0x1af": "eLiOq",
  "0x1b0": "AKpOd",
  "0x1b1": "BzmSR",
  "0x1b2": "</div>\n                        <div class=\"date\">",
  "0x1b3": "paste",
  "0x1b4": "isFinal",
  "0x1b5": "ZTmKE",
  "0x1b6": "warn",
  "0x1b7": "Enhance request failed:",
  "0x1b8": "\n                    <div style=\"text-align: center; padding: 20px;\">\n                        <div style=\"color: #ef4444; margin-bottom: 15px; font-weight: bold;\">⚠️ Erro do Sistema</div>\n                        <button id=\"retry-btn\" style=\"padding: 10px 20px; background: #27272a; border: 1px solid #3f3f46; color: white; border-radius: 8px; cursor: pointer;\">Recarregar Extensão</button>\n                    </div>\n                ",
  "0x1b9": "kSLdY",
  "0x1ba": "DjvHv",
  "0x1bb": "rOZqa",
  "0x1bc": "<div class=\"message-content\">Chat carregado: ",
  "0x1bd": "red",
  "0x1be": "qQdjK",
  "0x1bf": "Endpoint /source-code falhou, tentando /files...",
  "0x1c0": "/source-code",
  "0x1c1": "kEjZS",
  "0x1c2": "visible",
  "0x1c3": "JIyLt",
  "0x1c4": "❌ Erro no download: ",
  "0x1c5": "wxBfL",
  "0x1c6": "MGRKs",
  "0x1c7": "JfoyD",
  "0x1c8": "/files",
  "0x1c9": "pop",
  "0x1ca": "UcYZq",
  "0x1cb": "QVKIg",
  "0x1cc": "hpjjx",
  "0x1cd": "onend",
  "0x1ce": "Ismkx",
  "0x1cf": "SpOug",
  "0x1d0": "fuCQw",
  "0x1d1": "IddCg",
  "0x1d2": "mIqhI",
  "0x1d3": "EXEPm",
  "0x1d4": "path",
  "0x1d5": "kczEN",
  "0x1d6": "YRQKU",
  "0x1d7": "licenseKey",
  "0x1d8": "\n                            <div style=\"text-align: center; padding: 20px;\">\n                                <div style=\"color: #ef4444; margin-bottom: 10px; font-weight: bold;\">⚠️ Erro de Conexão</div>\n                                <div style=\"color: #94a3b8; font-size: 12px; margin-bottom: 20px;\">Não foi possível verificar sua licença. Verifique sua internet.</div>\n                                <button id=\"retry-btn\" style=\"padding: 10px 20px; background: #ef4444; border: none; color: black; font-weight: bold; border-radius: 8px; cursor: pointer; transition: transform 0.2s;\">TENTAR NOVAMENTE</button>\n                            </div>\n                         ",
  "0x1d9": "Bearer 9SUVXksWlAYFPRiacUm05ZKbVPqiuUQg",
  "0x1da": "pt-BR",
  "0x1db": "jxDgv",
  "0x1dc": "click",
  "0x1dd": "https://api.lovable.dev/projects/",
  "0x1de": "<div class=\"empty-history\">Nenhum histórico.</div>",
  "0x1df": "addEventListener",
  "0x1e0": "6090yUMCed",
  "0x1e1": "nPxnh",
  "0x1e2": "14432JNlcSS",
  "0x1e3": "accept",
  "0x1e4": "downloading",
  "0x1e5": "RwMVh",
  "0x1e6": "pasted-image-",
  "0x1e7": "LjPJk",
  "0x1e8": "kYrri",
  "0x1e9": "CbpGx",
  "0x1ea": "dfepT",
  "0x1eb": "wnPsu",
  "0x1ec": "ODmJG",
  "0x1ed": "*/*",
  "0x1ee": "loading",
  "0x1ef": "querySelector",
  "0x1f0": "undo-btn",
  "0x1f1": "arrwq",
  "0x1f2": "background",
  "0x1f3": "SqBCV",
  "0x1f4": "TvBxs",
  "0x1f5": "sInOG",
  "0x1f6": "dggFI",
  "0x1f7": "VBsEx",
  "0x1f8": "uYyRJ",
  "0x1f9": "</div>",
  "0x1fa": "QzNeC",
  "0x1fb": "display",
  "0x1fc": "get",
  "0x1fd": "close-image-btn",
  "0x1fe": "catch",
  "0x1ff": "currentTarget",
  "0x200": "cors",
  "0x201": "local",
  "0x202": "iTfmj",
  "0x203": "xBjVe",
  "0x204": "umoHE",
  "0x205": "uIkMA",
  "0x206": "Qynjl",
  "0x207": "now",
  "0x208": "match",
  "0x209": "uaZIU",
  "0x20a": "auto",
  "0x20b": "VBJza",
  "0x20c": "aENIU",
  "0x20d": "toString",
  "0x20e": "BMdvz",
  "0x20f": "TWvZT",
  "0x210": "YqPFL",
  "0x211": "1608753wCJHxo",
  "0x212": "LyjdK",
  "0x213": "0|1|4|2|3",
  "0x214": "history-btn",
  "0x215": "toUpperCase",
  "0x216": "Digite sua mensagem...",
  "0x217": "history-list",
  "0x218": "dDTDs",
  "0x219": "content",
  "0x21a": "contents",
  "0x21b": "[Audio] Permissão pendente ou negada via getUserMedia.",
  "0x21c": "recording",
  "0x21d": "readAsDataURL",
  "0x21e": "oWumI",
  "0x21f": "EEpKb",
  "0x220": "UsQYm",
  "0x221": "</div>\n                    </div>\n                    <button class=\"delete-chat-btn\" title=\"Excluir Chat\">&times;</button>\n                ",
  "0x222": "Microfone autorizado! Tentando conectar...",
  "0x223": "Microfone bloqueado! Clique para autorizar.",
  "0x224": "RmOco",
  "0x225": "BvswG",
  "0x226": "message-text",
  "0x227": "getTime",
  "0x228": "LZKzZ",
  "0x229": "EVhxa",
  "0x22a": "generateAsync",
  "0x22b": "not-allowed",
  "0x22c": "---",
  "0x22d": "setAttribute",
  "0x22e": "push",
  "0x22f": "JhoeN",
  "0x230": "onclick",
  "0x231": "querySelectorAll",
  "0x232": "qbwBE",
  "0x233": "getURL",
  "0x234": "Novo chat iniciado.",
  "0x235": "dFuJU",
  "0x236": "ArdTQ",
  "0x237": "revokeObjectURL",
  "0x238": "function",
  "0x239": "GWkog",
  "0x23a": "result",
  "0x23b": "/deployments?async=true",
  "0x23c": "tabs",
  "0x23d": "iYVEo",
  "0x23e": "toISOString",
  "0x23f": "ZnhnD",
  "0x240": "contains",
  "0x241": "uYfGj",
  "0x242": "publish-btn",
  "0x243": "mtsqN",
  "0x244": "Oiudq",
  "0x245": "log",
  "0x246": "webkitSpeechRecognition",
  "0x247": "all",
  "0x248": "syDTL",
  "0x249": "isAuthenticated",
  "0x24a": "ylElT",
  "0x24b": "stop",
  "0x24c": "WAsCx",
  "0x24d": "LfvAv",
  "0x24e": "removeAttribute",
  "0x24f": "connection_error",
  "0x250": "new-chat-btn",
  "0x251": "wlVSC",
  "0x252": "\" alt=\"preview\">\n                        <span class=\"file-name\" title=\"",
  "0x253": "dbNDS",
  "0x254": "xlkgk",
  "0x255": "❌ Erro de rede ao publicar: ",
  "0x256": "POST",
  "0x257": "[Audio] Falha ao iniciar:",
  "0x258": "color",
  "0x259": "lUBKp",
  "0x25a": "download",
  "0x25b": "zSvxG",
  "0x25c": "GET",
  "0x25d": "qbOvP",
  "0x25e": "json",
  "0x25f": "❌ Falha no Publish: ",
  "0x260": "credits-badge",
  "0x261": "/files/raw?path=",
  "0x262": "eOSNV",
  "0x263": "appendChild",
  "0x264": "SxUQF",
  "0x265": "Nenhum arquivo foi baixado com sucesso.",
  "0x266": "delete-chat-btn",
  "0x267": "HIprr",
  "0x268": "permission.html",
  "0x269": "credits",
  "0x26a": "RYjzp",
  "0x26b": "SkKFB",
  "0x26c": "AAUpx",
  "0x26d": "2-digit",
  "0x26e": "Lohav",
  "0x26f": "HOkWP",
  "0x270": "interimResults",
  "0x271": "Não foi possível obter a lista de arquivos do projeto. Tente novamente ou verifique suas permissões.",
  "0x272": "file",
  "0x273": "span",
  "0x274": "runtime",
  "0x275": "shiftKey",
  "0x276": "Erro rede ",
  "0x277": "set",
  "0x278": "active",
  "0x279": "VOsFx",
  "0x27a": "pointer",
  "0x27b": "endsWith",
  "0x27c": "change",
  "0x27d": "</span>\n                        <button class=\"remove-file-btn\" data-index=\"",
  "0x27e": "history-item",
  "0x27f": ".zip",
  "0x280": "ySUun",
  "0x281": "ZImbg",
  "0x282": "IeczH",
  "0x283": "type",
  "0x284": "removeChild",
  "0x285": "bDLpW",
  "0x286": "textContent",
  "0x287": "send-btn",
  "0x288": "NIrty",
  "0x289": "qhxvs",
  "0x28a": "scrollHeight",
  "0x28b": "Erro ao listar:",
  "0x28c": "file-name-small",
  "0x28d": "lovable_token",
  "0x28e": "ggxay",
  "0x28f": "gHxDS",
  "0x290": "UToji",
  "0x291": "pGMaf",
  "0x292": "iSdAY",
  "0x293": "Mistral Error:",
  "0x294": "popup",
  "0x295": "JxCwe",
  "0x296": "afKwt",
  "0x297": "okeCU",
  "0x298": "placeholder",
  "0x299": "blob",
  "0x29a": "JcGZM",
  "0x29b": "slice",
  "0x29c": "pIYmU",
  "0x29d": "image",
  "0x29e": "rVKeg",
  "0x29f": "LlSSu",
  "0x2a0": "close-history-btn",
  "0x2a1": "hicjQ",
  "0x2a2": "url",
  "0x2a3": "jxUNB",
  "0x2a4": "true",
  "0x2a5": "https://api.mistral.ai/v1/chat/completions",
  "0x2a6": "XHPru",
  "0x2a7": "zRaNc",
  "0x2a8": "[Audio] Erro:",
  "0x2a9": "className",
  "0x2aa": "modal-img",
  "0x2ab": "qxDzu",
  "0x2ac": "JiydF",
  "0x2ad": "action",
  "0x2ae": "trim",
  "0x2af": "tOHEV",
  "0x2b0": "RjEAY",
  "0x2b1": "lTXch",
  "0x2b2": "XMOOB",
  "0x2b3": "HyMEf",
  "0x2b4": "OxLrb",
  "0x2b5": "stopPropagation",
  "0x2b6": "nNVzN",
  "0x2b7": "afbKl",
  "0x2b8": "status-badge",
  "0x2b9": "BvNjk",
  "0x2ba": "Falha ",
  "0x2bb": "nHHLm",
  "0x2bc": "Enviado com sucesso!",
  "0x2bd": "RbViu",
  "0x2be": "u=1, i",
  "0x2bf": "sSGMs",
  "0x2c0": "storage",
  "0x2c1": "Erro desconhecido",
  "0x2c2": "TSuHo",
  "0x2c3": "KHHFj",
  "0x2c4": "dataset",
  "0x2c5": "Erro: Token ou ID do projeto não encontrados. Recarregue a página do Lovable.",
  "0x2c6": "split",
  "0x2c7": "HYBgi",
  "0x2c8": "HfpTH",
  "0x2c9": "yntTd",
  "0x2ca": "undefined",
  "0x2cb": "chatHistory",
  "0x2cc": "jHspn",
  "0x2cd": "updatedAt",
  "0x2ce": "getAsFile",
  "0x2cf": "crjZt",
  "0x2d0": "size",
  "0x2d1": "rgba(161, 161, 170, 0.1)",
  "0x2d2": "MmsFO",
  "0x2d3": "uAgsU",
  "0x2d4": "Clfns",
  "0x2d5": "gMdmG",
  "0x2d6": "clipboardData",
  "0x2d7": "no-speech",
  "0x2d8": "3261430iNBkXo",
  "0x2d9": "deviceId",
  "0x2da": "azWDr",
  "0x2db": "resultIndex",
  "0x2dc": "zsffA",
  "0x2dd": "cplmV",
  "0x2de": "Erro: Biblioteca JSZip não carregada.",
  "0x2df": "flex",
  "0x2e0": ".png",
  "0x2e1": "Bearer ",
  "0x2e2": "lovable-project-",
  "0x2e3": "KoizN",
  "0x2e4": "string",
  "0x2e5": "Ouvindo...",
  "0x2e6": "Enter",
  "0x2e7": "NDuLS",
  "0x2e8": "vmqXo",
  "0x2e9": "VHhUY",
  "0x2ea": "body",
  "0x2eb": "add",
  "0x2ec": "nRiYS",
  "0x2ed": "value",
  "0x2ee": "bBidW",
  "0x2ef": "NRDHn",
  "0x2f0": ".delete-chat-btn",
  "0x2f1": "application/json",
  "0x2f2": "rkRvA",
  "0x2f3": "create",
  "0x2f4": "chat-container",
  "0x2f5": "rgba(161, 161, 170, 0.2)",
  "0x2f6": "ILpvp",
  "0x2f7": "src",
  "0x2f8": "\n                        <div class=\"file-icon\" style=\"width:40px;height:40px;display:flex;align-items:center;justify-content:center;background:rgba(239,68,68,0.15);border-radius:6px;font-size:10px;font-weight:bold;color:#ef4444;flex-shrink:0;\">",
  "0x2f9": ".remove-file-btn",
  "0x2fa": "ySsQR",
  "0x2fb": "wvboc",
  "0x2fc": "CSbOU",
  "0x2fd": "download-project-btn",
  "0x2fe": "PNjMI",
  "0x2ff": "vqLmQ",
  "0x300": "style",
  "0x301": "#a1a1aa",
  "0x302": "alt",
  "0x303": "KUwbL",
  "0x304": "Novo Chat",
  "0x305": "file-preview-chip",
  "0x306": "reload",
  "0x307": "volEd",
  "0x308": "status",
  "0x309": "ltVMK",
  "0x30a": "LdGME",
  "0x30b": "onChanged",
  "0x30c": "message",
  "0x30d": "from",
  "0x30e": "10EQWvdW",
  "0x30f": "XmzCz"
}